TakeBlipNer/__init__.py
TakeBlipNer/data.py
TakeBlipNer/nermodel.py
TakeBlipNer/utils.py
TakeBlipNer/vocab.py
TakeBlipNer/logger/AzuremlLogger.py
TakeBlipNer/logger/__init__.py
TakeBlipNer/predict/NerPredict.py
TakeBlipNer/predict/__init__.py
TakeBlipNer/train/LSTMCRFTrainer.py
TakeBlipNer/train/__init__.py
TakeBlipNer-0.0.6.dist-info/LICENSE
TakeBlipNer-0.0.6.dist-info/METADATA
TakeBlipNer-0.0.6.dist-info/WHEEL
TakeBlipNer-0.0.6.dist-info/top_level.txt
TakeBlipNer-0.0.6.dist-info/RECORD
