Metadata-Version: 2.1
Name: TakeBlipNer
Version: 0.0.6
Summary: Named Entity Recognition Package
Home-page: UNKNOWN
Author: Data and Analytics Research
Author-email: analytics.dar@take.net
License: UNKNOWN
Keywords: ner
Platform: UNKNOWN
Classifier: Programming Language :: Python :: 3
Classifier: License :: OSI Approved :: MIT License
Classifier: Operating System :: OS Independent
License-File: LICENSE
Requires-Dist: pyaap
Requires-Dist: tqdm
Requires-Dist: gensim (==3.8.3)
Requires-Dist: TakeSentenceTokenizer (==1.0.1)
Requires-Dist: tensorboard
